odoo/addons/account_invoice_prepare/LICENSE
odoo/addons/account_invoice_prepare/README.rst
odoo/addons/account_invoice_prepare/__init__.py
odoo/addons/account_invoice_prepare/__manifest__.py
odoo/addons/account_invoice_prepare/data/account_report.xml
odoo/addons/account_invoice_prepare/data/ir_actions.xml
odoo/addons/account_invoice_prepare/i18n/de.po
odoo/addons/account_invoice_prepare/images/screen.png
odoo/addons/account_invoice_prepare/models/__init__.py
odoo/addons/account_invoice_prepare/models/account_move.py
odoo/addons/account_invoice_prepare/static/description/icon.png
odoo/addons/account_invoice_prepare/static/description/index.html
odoo/addons/account_invoice_prepare/tests/TEST_INSTRUCTIONS.rst
odoo/addons/account_invoice_prepare/views/account_move_views.xml
odoo_addon_account_invoice_prepare-18.0.1.0.0.dist-info/METADATA
odoo_addon_account_invoice_prepare-18.0.1.0.0.dist-info/WHEEL
odoo_addon_account_invoice_prepare-18.0.1.0.0.dist-info/top_level.txt
odoo_addon_account_invoice_prepare-18.0.1.0.0.dist-info/RECORD
